socialstats/__init__.py
socialstats/constant.py
socialstats/main.py
socialstats/base/__init__.py
socialstats/base/director_interface.py
socialstats/base/proxy_mixin.py
socialstats/base/user.py
socialstats/codechef/__init__.py
socialstats/codechef/cc_builder.py
socialstats/codechef/cc_director.py
socialstats/codechef/cc_user.py
socialstats/codeforces/__init__.py
socialstats/codeforces/cf_builder.py
socialstats/codeforces/cf_director.py
socialstats/codeforces/cf_user.py
socialstats/factories/__init__.py
socialstats/factories/user_factory.py
socialstats/leetcode/__init__.py
socialstats/leetcode/leet_builder.py
socialstats/leetcode/leet_director.py
socialstats/leetcode/leet_user.py
socialstats/medium/__init__.py
socialstats/medium/medium_builder.py
socialstats/medium/medium_director.py
socialstats/medium/medium_user.py
socialstats/stackoverflow/__init__.py
socialstats/stackoverflow/stack_builder.py
socialstats/stackoverflow/stack_director.py
socialstats/stackoverflow/stack_user.py
socialstats/twitter/__init__.py
socialstats/twitter/twitter_builder.py
socialstats/twitter/twitter_director.py
socialstats/twitter/twitter_user.py
social_stats-0.0.4.dist-info/LICENSE
social_stats-0.0.4.dist-info/METADATA
social_stats-0.0.4.dist-info/WHEEL
social_stats-0.0.4.dist-info/entry_points.txt
social_stats-0.0.4.dist-info/top_level.txt
social_stats-0.0.4.dist-info/RECORD
